ms_shared_nb/__init__.py
ms_shared_nb/charts.py
ms_shared_nb/custom_widgets/__init__.py
ms_shared_nb/custom_widgets/caching.py
ms_shared_nb/custom_widgets/grids.py
ms_shared_nb/custom_widgets/scrollable_display.py
ms_shared_nb/defines.py
ms_shared_nb/eda/__init__.py
ms_shared_nb/eda/df_analyzer.py
ms_shared_nb/eda/df_filtering.py
ms_shared_nb/eda/eda_plots.py
ms_shared_nb/eda/eda_widgets.py
ms_shared_nb/eda/utils.py
ms_shared_nb/sampling/sample_configs.py
ms_shared_nb/sampling/sample_plots.py
ms_shared_nb/sampling/sample_split.py
ms_shared_nb/sampling/samples_widget.py
ms_shared_nb/sampling/util.py
ms_shared_nb/xls_reader.py
ms_shared_nb-0.1.4.dist-info/METADATA
ms_shared_nb-0.1.4.dist-info/WHEEL
ms_shared_nb-0.1.4.dist-info/RECORD
