Metadata-Version: 2.1
Name: ms-shared-nb
Version: 0.1.4
Summary: 
Author: smudit
Author-email: mudit.sharma@btinternet.com
Requires-Python: >=3.11,<4.0
Classifier: Programming Language :: Python :: 3
Classifier: Programming Language :: Python :: 3.11
Classifier: Programming Language :: Python :: 3.12
Classifier: Programming Language :: Python :: 3.13
Requires-Dist: hvplot (>=0.9.1,<0.10.0)
Requires-Dist: ipydatagrid (>=1.3.2,<2.0.0)
Requires-Dist: ipython (>=8.26.0,<9.0.0)
Requires-Dist: matplotlib (>=3.8.2,<4.0.0)
Requires-Dist: plotly (>=5.18.0,<6.0.0)
Requires-Dist: seaborn (>=0.13.1,<0.14.0)
